{
  "genre": {
    "science fiction": ["science fiction","sci fi","sci-fi","sf","scifi"],
    "fantasy": ["fantasy","high fantasy","low fantasy","epic fantasy"],
    "mystery": ["mystery","detective","whodunit"],
    "romance": ["romance","love story"],
    "thriller": ["thriller","suspense"],
    "historical": ["historical","historical fiction"],
    "nonfiction": ["nonfiction","non-fiction","nf"],
    "biography": ["biography","bio","life of"],
    "children": ["children","kids","picture book","picture-book","picturebook"],
    "textbook": ["textbook","course text","manual"]
  },
  "audience": {
    "children": ["children","kids","picture-book","picture book"],
    "middle-grade": ["middle grade","mg"],
    "YA": ["ya","young adult"],
    "adult": ["adult","general"],
    "academic": ["academic","college","university","graduate"]
  },
  "tone_style": {
    "epic": ["epic","sweeping","grand"],
    "whimsical": ["whimsical","playful"],
    "dark": ["dark","grim","noir"],
    "humorous": ["humorous","funny","comic"],
    "instructional": ["instructional","didactic","how-to"],
    "lyrical": ["lyrical","poetic"],
    "technical": ["technical","rigorous"]
  }
}
